selenium_scrapy/__init__.py
selenium_scrapy/http.py
selenium_scrapy/middlewares.py
selenium_scrapy-0.1.4.dist-info/METADATA
selenium_scrapy-0.1.4.dist-info/WHEEL
selenium_scrapy-0.1.4.dist-info/top_level.txt
selenium_scrapy-0.1.4.dist-info/zip-safe
selenium_scrapy-0.1.4.dist-info/RECORD
