Metadata-Version: 2.1
Name: selenium-scrapy
Version: 0.1.4
Summary: Scrapy with selenium==4.3
Home-page: https://github.com/mrafee113/selenium_scrapy
Requires-Dist: Scrapy (==2.6.1)
Requires-Dist: pyselenium-localstorage (==0.1.1)
